algocore/__init__.py
algocore/decorators.py
algocore/functions.py
algocore/utils.py
algocore-0.1.0.dist-info/licenses/LICENSE
algocore-0.1.0.dist-info/METADATA
algocore-0.1.0.dist-info/WHEEL
algocore-0.1.0.dist-info/top_level.txt
algocore-0.1.0.dist-info/RECORD
