Metadata-Version: 2.4
Name: algocore
Version: 0.1.0
Summary: High-performance image processing functions for deep learning and computer vision.
Author-email: Ben Elfner <algorave@belfner.com>
Maintainer-email: Ben Elfner <algorave@belfner.com>
License: MIT License
Keywords: deep learning,image processing
Classifier: Development Status :: 5 - Production/Stable
Classifier: Intended Audience :: Developers
Classifier: Intended Audience :: Science/Research
Classifier: License :: OSI Approved :: MIT License
Classifier: Operating System :: OS Independent
Classifier: Programming Language :: Python
Classifier: Programming Language :: Python :: 3 :: Only
Classifier: Programming Language :: Python :: 3.9
Classifier: Programming Language :: Python :: 3.10
Classifier: Programming Language :: Python :: 3.11
Classifier: Programming Language :: Python :: 3.12
Classifier: Programming Language :: Python :: 3.13
Classifier: Topic :: Scientific/Engineering :: Artificial Intelligence
Classifier: Topic :: Scientific/Engineering :: Image Processing
Classifier: Topic :: Software Development :: Libraries
Classifier: Topic :: Software Development :: Libraries :: Python Modules
Classifier: Typing :: Typed
Requires-Python: >=3.9
License-File: LICENSE
Requires-Dist: numpy>=1.24.4
Requires-Dist: typing-extensions>=4.9.0; python_version < "3.10"
Requires-Dist: stringzilla>=3.10.4
Requires-Dist: simsimd>=5.9.2
Requires-Dist: opencv-python>=4.9.0.80
Dynamic: license-file
Dynamic: requires-dist
